{
   "data": [
      {
         "from": {
            "name": "Mouni Chag",
            "id": "131449200608913"
         },
         "created_time": "2016-06-16T11:19:53+0000",
         "updated_time": "2016-06-16T16:10:51+0000",
         "link": "https://www.facebook.com/photo.php?fbid=139155069838326&set=a.139155106504989.1073741830.100012315016420&type=3",
         "object_id": "139155069838326",
         "type": "photo",
         "id": "131449200608913_139155109838322",
         "reactions": {
            "data": [
               {
                  "id": "114267698998620",
                  "name": "Mantra Mantra",
                  "type": "LOVE"
               }
            ],
            "paging": {
               "cursors": {
                  "before": "TVRBd01ERXlORFl4TnpBME5qWTRPakUwTmpZAd09UTTBNekU2TnpnNE5qUTRNRE0zT1RFek16RXkZD",
                  "after": "TVRBd01ERXlORFl4TnpBME5qWTRPakUwTmpZAd09UTTBNekU2TnpnNE5qUTRNRE0zT1RFek16RXkZD"
               }
            }
         },
         "comments": {
            "data": [
               {
                  "created_time": "2016-06-16T16:10:51+0000",
                  "from": {
                     "name": "Mantra Mantra",
                     "id": "114267698998620"
                  },
                  "message": "vibrant color.. beautiful",
                  "id": "139155069838326_139392946481205"
               }
            ],
            "paging": {
               "cursors": {
                  "before": "WTI5dGJXVnVkRjlqZAFhKemIzSTZANVE01TXpreU9UUTJORGd4TWpBMU9qRTBOall3T1RNME5UST0ZD",
                  "after": "WTI5dGJXVnVkRjlqZAFhKemIzSTZANVE01TXpreU9UUTJORGd4TWpBMU9qRTBOall3T1RNME5UST0ZD"
               }
            }
         }
      },
      {
         "from": {
            "name": "Mouni Chag",
            "id": "131449200608913"
         },
         "created_time": "2016-06-16T11:19:21+0000",
         "updated_time": "2016-06-16T11:19:21+0000",
         "link": "https://www.facebook.com/photo.php?fbid=139154236505076&set=a.139154246505075.1073741829.100012315016420&type=3",
         "object_id": "139154236505076",
         "type": "photo",
         "id": "131449200608913_139154249838408"
      },
      {
         "from": {
            "name": "Mouni Chag",
            "id": "131449200608913"
         },
         "created_time": "2016-06-16T10:15:35+0000",
         "updated_time": "2016-06-16T10:15:35+0000",
         "type": "status",
         "id": "131449200608913_139110669842766"
      },
      {
         "from": {
            "name": "Mouni Chag",
            "id": "131449200608913"
         },
         "created_time": "2016-06-16T06:19:42+0000",
         "updated_time": "2016-06-16T06:19:42+0000",
         "link": "https://www.facebook.com/LAInternationalAirport/",
         "type": "link",
         "id": "131449200608913_138979273189239"
      },
      {
         "from": {
            "name": "Mouni Chag",
            "id": "131449200608913"
         },
         "created_time": "2016-06-16T06:18:42+0000",
         "updated_time": "2016-06-16T06:21:33+0000",
         "place": {
            "id": "74286767824",
            "name": "Los Angeles International Airport (LAX)",
            "location": {
               "city": "Los Angeles",
               "country": "United States",
               "latitude": 33.9442368,
               "longitude": -118.3975983,
               "state": "CA",
               "zip": "90045"
            }
         },
         "type": "status",
         "id": "131449200608913_138979086522591",
         "reactions": {
            "data": [
               {
                  "id": "1055982414493113",
                  "name": "Chaganti Harika",
                  "type": "LOVE"
               },
               {
                  "id": "131449200608913",
                  "name": "Mouni Chag",
                  "type": "LIKE"
               }
            ],
            "paging": {
               "cursors": {
                  "before": "TVRBd01EQXlORFF3T1RJM016VXlPakUwTmpZAd05UYzVPVEU2TnpnNE5qUTRNRE0zT1RFek16RXkZD",
                  "after": "TVRBd01ERXlNekUxTURFMk5ESXdPakUwTmpZAd05UYzVOekE2TWpVME1EazJNVFl4TXc9PQZDZD"
               }
            }
         },
         "likes": {
            "data": [
               {
                  "id": "131449200608913",
                  "name": "Mouni Chag"
               }
            ],
            "paging": {
               "cursors": {
                  "before": "MTMxNDQ5MjAwNjA4OTEz",
                  "after": "MTMxNDQ5MjAwNjA4OTEz"
               }
            }
         },
         "comments": {
            "data": [
               {
                  "created_time": "2016-06-16T06:19:24+0000",
                  "from": {
                     "name": "Chaganti Harika",
                     "id": "1055982414493113"
                  },
                  "message": ":*",
                  "id": "138979086522591_138979226522577"
               }
            ],
            "paging": {
               "cursors": {
                  "before": "WTI5dGJXVnVkRjlqZAFhKemIzSTZANVE00T1RjNU1qSTJOVEl5TlRjM09qRTBOall3TlRjNU5qUT0ZD",
                  "after": "WTI5dGJXVnVkRjlqZAFhKemIzSTZANVE00T1RjNU1qSTJOVEl5TlRjM09qRTBOall3TlRjNU5qUT0ZD"
               }
            }
         }
      },
      {
         "from": {
            "name": "Mouni Chag",
            "id": "131449200608913"
         },
         "created_time": "2016-06-16T06:10:19+0000",
         "updated_time": "2016-06-16T06:16:05+0000",
         "link": "https://www.facebook.com/photo.php?fbid=138970046523495&set=a.138976093189557.1073741828.100012315016420&type=3",
         "object_id": "138970046523495",
         "type": "photo",
         "id": "131449200608913_138976293189537",
         "reactions": {
            "data": [
               {
                  "id": "131449200608913",
                  "name": "Mouni Chag",
                  "type": "LIKE"
               },
               {
                  "id": "1055982414493113",
                  "name": "Chaganti Harika",
                  "type": "LOVE"
               }
            ],
            "paging": {
               "cursors": {
                  "before": "TVRBd01ERXlNekUxTURFMk5ESXdPakUwTmpZAd05UYzNNalE2TWpVME1EazJNVFl4TXc9PQZDZD",
                  "after": "TVRBd01EQXlORFF3T1RJM016VXlPakUwTmpZAd05UYzJPRGs2TnpnNE5qUTRNRE0zT1RFek16RXkZD"
               }
            }
         },
         "likes": {
            "data": [
               {
                  "id": "131449200608913",
                  "name": "Mouni Chag"
               }
            ],
            "paging": {
               "cursors": {
                  "before": "MTMxNDQ5MjAwNjA4OTEz",
                  "after": "MTMxNDQ5MjAwNjA4OTEz"
               }
            }
         },
         "comments": {
            "data": [
               {
                  "created_time": "2016-06-16T06:13:55+0000",
                  "from": {
                     "name": "Chaganti Harika",
                     "id": "1055982414493113"
                  },
                  "message": "you always rock :)",
                  "id": "138976293189537_138977633189403"
               }
            ],
            "paging": {
               "cursors": {
                  "before": "WTI5dGJXVnVkRjlqZAFhKemIzSTZANVE00T1RjM05qTXpNVGc1TkRBek9qRTBOall3TlRjMk16VT0ZD",
                  "after": "WTI5dGJXVnVkRjlqZAFhKemIzSTZANVE00T1RjM05qTXpNVGc1TkRBek9qRTBOall3TlRjMk16VT0ZD"
               }
            }
         }
      },
      {
         "from": {
            "name": "Mouni Chag",
            "id": "131449200608913"
         },
         "created_time": "2016-06-16T06:09:36+0000",
         "updated_time": "2016-06-16T06:10:35+0000",
         "message": "enjoyed at my favourite place with my dearest ones :) \nhttps:graph.facebook.com",
         "link": "https://www.facebook.com/photo.php?fbid=138970046523495&set=a.138976093189557.1073741828.100012315016420&type=3",
         "place": {
            "id": "671588462870641",
            "name": "Visakhapatnam City of Destiny",
            "location": {
               "city": "Visakhapatnam",
               "country": "India",
               "latitude": 17.7,
               "longitude": 83.25,
               "street": "Beach Road",
               "zip": "530008"
            }
         },
         "object_id": "138970046523495",
         "type": "photo",
         "id": "131449200608913_138976096522890",
         "reactions": {
            "data": [
               {
                  "id": "114267698998620",
                  "name": "Mantra Mantra",
                  "type": "LOVE"
               },
               {
                  "id": "1055982414493113",
                  "name": "Chaganti Harika",
                  "type": "LIKE"
               },
               {
                  "id": "131449200608913",
                  "name": "Mouni Chag",
                  "type": "LOVE"
               }
            ],
            "paging": {
               "cursors": {
                  "before": "TVRBd01ERXlORFl4TnpBME5qWTRPakUwTmpZAeE1EQXpOamc2TnpnNE5qUTRNRE0zT1RFek16RXkZD",
                  "after": "TVRBd01ERXlNekUxTURFMk5ESXdPakUwTmpZAd05UYzBOakE2TnpnNE5qUTRNRE0zT1RFek16RXkZD"
               }
            }
         },
         "likes": {
            "data": [
               {
                  "id": "1055982414493113",
                  "name": "Chaganti Harika"
               }
            ],
            "paging": {
               "cursors": {
                  "before": "MTA1NTk4MjQxNDQ5MzExMwZDZD",
                  "after": "MTA1NTk4MjQxNDQ5MzExMwZDZD"
               }
            }
         },
         "comments": {
            "data": [
               {
                  "created_time": "2016-06-16T06:10:35+0000",
                  "from": {
                     "name": "Mouni Chag",
                     "id": "131449200608913"
                  },
                  "message": "super!!",
                  "id": "138976096522890_138976359856197"
               }
            ],
            "paging": {
               "cursors": {
                  "before": "WTI5dGJXVnVkRjlqZAFhKemIzSTZANVE00T1RjMk16VTVPRFUyTVRrM09qRTBOall3TlRjME16VT0ZD",
                  "after": "WTI5dGJXVnVkRjlqZAFhKemIzSTZANVE00T1RjMk16VTVPRFUyTVRrM09qRTBOall3TlRjME16VT0ZD"
               }
            }
         }
      },
      {
         "from": {
            "name": "Mouni Chag",
            "id": "131449200608913"
         },
         "created_time": "2016-06-16T05:22:30+0000",
         "updated_time": "2016-06-16T05:23:23+0000",
         "message": "IMG_3997.CR2",
         "link": "https://www.facebook.com/photo.php?fbid=138945929859240&set=a.138945919859241.1073741826.100012315016420&type=3",
         "object_id": "138945929859240",
         "type": "photo",
         "id": "131449200608913_138945929859240",
         "reactions": {
            "data": [
               {
                  "id": "131449200608913",
                  "name": "Mouni Chag",
                  "type": "LIKE"
               }
            ],
            "paging": {
               "cursors": {
                  "before": "TVRBd01ERXlNekUxTURFMk5ESXdPakUwTmpZAd05UUTFOelk2TWpVME1EazJNVFl4TXc9PQZDZD",
                  "after": "TVRBd01ERXlNekUxTURFMk5ESXdPakUwTmpZAd05UUTFOelk2TWpVME1EazJNVFl4TXc9PQZDZD"
               }
            }
         },
         "likes": {
            "data": [
               {
                  "id": "131449200608913",
                  "name": "Mouni Chag"
               }
            ],
            "paging": {
               "cursors": {
                  "before": "MTMxNDQ5MjAwNjA4OTEz",
                  "after": "MTMxNDQ5MjAwNjA4OTEz"
               }
            }
         },
         "comments": {
            "data": [
               {
                  "created_time": "2016-06-16T05:23:23+0000",
                  "from": {
                     "name": "Mouni Chag",
                     "id": "131449200608913"
                  },
                  "message": "Great click :)",
                  "id": "138945929859240_138946499859183"
               }
            ],
            "paging": {
               "cursors": {
                  "before": "WTI5dGJXVnVkRjlqZAFhKemIzSTZANVE00T1RRMk5EazVPRFU1TVRnek9qRTBOall3TlRRMk1ETT0ZD",
                  "after": "WTI5dGJXVnVkRjlqZAFhKemIzSTZANVE00T1RRMk5EazVPRFU1TVRnek9qRTBOall3TlRRMk1ETT0ZD"
               }
            }
         }
      },
      {
         "from": {
            "name": "Mouni Chag",
            "id": "131449200608913"
         },
         "created_time": "2016-06-09T14:21:28+0000",
         "updated_time": "2016-06-09T14:22:38+0000",
         "message": "Congratulations!! I wish you all the good luck :)",
         "type": "status",
         "id": "131449200608913_131682667252233",
         "reactions": {
            "data": [
               {
                  "id": "131449200608913",
                  "name": "Mouni Chag",
                  "type": "LIKE"
               }
            ],
            "paging": {
               "cursors": {
                  "before": "TVRBd01ERXlNekUxTURFMk5ESXdPakUwTmpVME9ESXhNakU2TWpVME1EazJNVFl4TXc9PQZDZD",
                  "after": "TVRBd01ERXlNekUxTURFMk5ESXdPakUwTmpVME9ESXhNakU2TWpVME1EazJNVFl4TXc9PQZDZD"
               }
            }
         },
         "likes": {
            "data": [
               {
                  "id": "131449200608913",
                  "name": "Mouni Chag"
               }
            ],
            "paging": {
               "cursors": {
                  "before": "MTMxNDQ5MjAwNjA4OTEz",
                  "after": "MTMxNDQ5MjAwNjA4OTEz"
               }
            }
         },
         "comments": {
            "data": [
               {
                  "created_time": "2016-06-09T14:22:21+0000",
                  "from": {
                     "name": "Mouni Chag",
                     "id": "131449200608913"
                  },
                  "message": "Thanks for your wishes..!",
                  "id": "131682667252233_131683377252162"
               }
            ],
            "paging": {
               "cursors": {
                  "before": "WTI5dGJXVnVkRjlqZAFhKemIzSTZANVE14Tmpnek16YzNNalV5TVRZAeU9qRTBOalUwT0RJeE5EST0ZD",
                  "after": "WTI5dGJXVnVkRjlqZAFhKemIzSTZANVE14Tmpnek16YzNNalV5TVRZAeU9qRTBOalUwT0RJeE5EST0ZD"
               }
            }
         }
      },
      {
         "from": {
            "name": "Mouni Chag",
            "id": "131449200608913"
         },
         "created_time": "2016-06-07T16:27:21+0000",
         "updated_time": "2016-06-07T16:27:21+0000",
         "message": "today's weather is good :)",
         "type": "status",
         "id": "131449200608913_128232900930543",
         "reactions": {
            "data": [
               {
                  "id": "131449200608913",
                  "name": "Mouni Chag",
                  "type": "LIKE"
               }
            ],
            "paging": {
               "cursors": {
                  "before": "TVRBd01ERXlNekUxTURFMk5ESXdPakUwTmpVek56QTBOVGc2TWpVME1EazJNVFl4TXc9PQZDZD",
                  "after": "TVRBd01ERXlNekUxTURFMk5ESXdPakUwTmpVek56QTBOVGc2TWpVME1EazJNVFl4TXc9PQZDZD"
               }
            }
         },
         "likes": {
            "data": [
               {
                  "id": "131449200608913",
                  "name": "Mouni Chag"
               }
            ],
            "paging": {
               "cursors": {
                  "before": "MTMxNDQ5MjAwNjA4OTEz",
                  "after": "MTMxNDQ5MjAwNjA4OTEz"
               }
            }
         }
      },
      {
         "from": {
            "name": "Mouni Chag",
            "id": "131449200608913"
         },
         "created_time": "2016-06-07T08:47:26+0000",
         "updated_time": "2016-06-08T13:31:52+0000",
         "message": "IMG_3997.CR2",
         "link": "https://www.facebook.com/photo.php?fbid=127489677671532&set=a.127489651004868.1073741825.100012315016420&type=3",
         "object_id": "127489677671532",
         "type": "photo",
         "id": "131449200608913_127489677671532",
         "reactions": {
            "data": [
               {
                  "id": "114267698998620",
                  "name": "Mantra Mantra",
                  "type": "LIKE"
               },
               {
                  "id": "131449200608913",
                  "name": "Mouni Chag",
                  "type": "WOW"
               }
            ],
            "paging": {
               "cursors": {
                  "before": "TVRBd01ERXlORFl4TnpBME5qWTRPakUwTmpVek9USTBNalU2TWpVME1EazJNVFl4TXc9PQZDZD",
                  "after": "TVRBd01ERXlNekUxTURFMk5ESXdPakUwTmpVeU9Ea3pNemM2TnpnNE5qUTRNRE0zT1RFek16RXkZD"
               }
            }
         },
         "likes": {
            "data": [
               {
                  "id": "114267698998620",
                  "name": "Mantra Mantra"
               }
            ],
            "paging": {
               "cursors": {
                  "before": "MTE0MjY3Njk4OTk4NjIw",
                  "after": "MTE0MjY3Njk4OTk4NjIw"
               }
            }
         },
         "comments": {
            "data": [
               {
                  "created_time": "2016-06-07T08:48:36+0000",
                  "from": {
                     "name": "Mouni Chag",
                     "id": "131449200608913"
                  },
                  "message": "beautiful pic",
                  "id": "127489677671532_127492171004616"
               },
               {
                  "created_time": "2016-06-07T08:48:42+0000",
                  "from": {
                     "name": "Mouni Chag",
                     "id": "131449200608913"
                  },
                  "message": "thank you",
                  "id": "127489677671532_127492251004608"
               },
               {
                  "created_time": "2016-06-08T13:31:52+0000",
                  "from": {
                     "name": "Mantra Mantra",
                     "id": "114267698998620"
                  },
                  "message": "Very beautiful picture. I like it. :)",
                  "id": "127489677671532_129855150768318"
               }
            ],
            "paging": {
               "cursors": {
                  "before": "WTI5dGJXVnVkRjlqZAFhKemIzSTZANVEkzTkRreU1UY3hNREEwTmpFMk9qRTBOalV5T0Rrek1UWT0ZD",
                  "after": "WTI5dGJXVnVkRjlqZAFhKemIzSTZANVEk1T0RVMU1UVXdOelk0TXpFNE9qRTBOalV6T1RJM01UST0ZD"
               }
            }
         }
      },
      {
         "from": {
            "name": "Mouni Chag",
            "id": "131449200608913"
         },
         "created_time": "2014-12-31T20:00:00+0000",
         "updated_time": "2014-12-31T20:00:00+0000",
         "link": "https://www.facebook.com/131449200608913/timeline/story?ut=32&wstart=-2051193600&wend=2147483647&hash=137489656671534&pagefilter=3&ustart=1",
         "object_id": "137489656671534",
         "type": "link",
         "id": "131449200608913_137489656671534"
      },
      {
         "from": {
            "name": "Mouni Chag",
            "id": "131449200608913"
         },
         "created_time": "2010-01-01T08:00:00+0000",
         "updated_time": "2010-01-01T08:00:00+0000",
         "link": "https://www.facebook.com/131449200608913/timeline/story?ut=32&wstart=-2051193600&wend=2147483647&hash=137489656671534&pagefilter=3&ustart=1",
         "object_id": "137489656671534",
         "type": "link",
         "id": "131449200608913_137489656671534"
      },
      {
         "from": {
            "name": "Mouni Chag",
            "id": "131449200608913"
         },
         "created_time": "1990-01-01T08:00:00+0000",
         "updated_time": "1990-01-01T08:00:00+0000",
         "link": "https://www.facebook.com/131449200608913/posts/127134587707041",
         "object_id": "127134587707041",
         "type": "link",
         "id": "131449200608913_127134587707041"
      }
   ],
   "paging": {
      "previous": "https://graph.facebook.com/v2.6/131449200608913/posts?fields=from,created_time,updated_time,message,link,place,object_id,likes,reactions,comments,type&since=1466075993&access_token=EAAOt19E3ZCckBAJm1rUB5YXKmaxrfZC8IPwiyo6QC5SVS90KknjZAP5kCZB4tLzxSMJ0ryDhlntqYDN6O520UIx1CQZC089QhAEJwQ5wMEW7j7PSgd5eBNKSqtZBJtPuAVbIcye40mIV8UxsT4uvGZBkuaUvNWGTcgZD&limit=25&__paging_token=enc_AdDkm9ZCFCoBWS4VZAgI3l1hLDcZCYE5xmHSXGgZCdq8LyIHtorDtfehap2FZC0ZBoOO950UAchm1lmALivZBJn5Qxpqqq3eISW493cwDaZCvpJ4R6EMsQZDZD&__previous=1",
      "next": "https://graph.facebook.com/v2.6/131449200608913/posts?fields=from,created_time,updated_time,message,link,place,object_id,likes,reactions,comments,type&access_token=EAAOt19E3ZCckBAJm1rUB5YXKmaxrfZC8IPwiyo6QC5SVS90KknjZAP5kCZB4tLzxSMJ0ryDhlntqYDN6O520UIx1CQZC089QhAEJwQ5wMEW7j7PSgd5eBNKSqtZBJtPuAVbIcye40mIV8UxsT4uvGZBkuaUvNWGTcgZD&limit=25&until=631180800&__paging_token=enc_AdBOxYxMFyBmuJcR35JiNVTN2dkRIGHKdJP0yVgTqZAS286ZCCYwZCKFnzwJZCSoPqj1SjHpuoO8dDZBWHyMZBHu4nOiMEtazPkKknzExXwXc0pZBKZCZCQZDZD"
   }
}